Workbook

Sheet Integrantes
A1: Integrantes
A2: Felipe Freitas Silva
A3: Luiza Heller Kroeff Plá
A4: Marcius Moraes Vargas

Sheet T Base (enunciado)
B2: Produtos | C2: Custo Variável Direto Unitário | D2: Fabricação | E2: Montagem
C4: ($ por unidade) | D4: (horas por unidade)
B6: A | C6: 25 | D6: =15/60 -> 0.25 | E6: =10/60 -> 0.16666667
B7: B | C7: 100 | D7: =30/60 -> 0.5 | E7: =40/60 -> 0.66666667
B9: Custo Fixo Direto | D9: ($ por mês)
D11: 4000 | E11: 5600
B13: Capacidade Instalada | D13: (horas por mês)
D15: 200 | E15: 200
B17: Custo Fixo Indireto | D17: ($ por mês)
D19: 4800
C21: Produtos | D21: Preço de Venda Unitário | E21: Demanda Estimada
D23: ($ por unidade) | E23: (unidades por mês)
C25: A | D25: 100 | E25: 200
C26: B | D26: 200 | E26: 150
B28: ϖA = | C28: =E25*(D25-C6) -> 15000
B29: ϖB = | C29: =E26*(D26-C7) -> 15000
B30: ϖ = | C30: =C28+C29-(D11+E11+D19) -> 15600

Sheet T Participações Relativas
E2: A | F2: B
B4: Preço de venda unitário (P) ($por unidade) | E4: ='T Base (enunciado)'!D25 -> 100 | F4: ='T Base (enunciado)'!D26 -> 200
B5: Custo variável unitário (V) ($por unidade) | E5: ='T Base (enunciado)'!C6 -> 25 | F5: ='T Base (enunciado)'!C7 -> 100
B7: Margem de contribuição unitária ($por unidade) (MCU = P - V) | E7: =E4-E5 -> 75 | F7: =F4-F5 -> 100
B9: Razão de Contribuição (RC = MCU/P) | E9: =E7/E4 -> 0.75 | F9: =F7/F4 -> 0.5
B12: Demanda Estimada (Q) (unidades por mês) | E12: ='T Base (enunciado)'!E25 -> 200 | F12: ='T Base (enunciado)'!E26 -> 150
B14: Receita total estimada (R = Q x P) ($por mês) | E14: =E12*E4 -> 20000 | F14: =F12*F4 -> 30000
B15: Participação Relativa (na receita total estimada) | E15: =E14/(E14+F14) -> 0.4 | F15: =F14/(E14+F14) -> 0.6

Sheet T CR&AC
B2: Tabela de Consumo de Recursos e Alocação dos Custos Fixos Diretos de Produção dos Produtos
B4: Produtos | C4: Demanda Estimada | D4: Consumo Recursos Fabricação | E4: Proporção do Consumo Fabricação | F4: Custo Fixo Direto Fabricação | G4: Consumo Recursos Montagem | H4: Proporção do Consumo Montagem | I4: Custo Fixo Direto Montagem | J4: Custo Fixo Direto por Produto
C6: (unidades por mês) | D6: (horas por mês) | E6: (% sobre o total) | F6: ($ por mês) | G6: (horas por mês) | H6: (% sobre o total) | I6: ($ por mês) | J6: ($ por mês)
B8: A | C8: ='T Base (enunciado)'!E25 -> 200 | D8: ='T Base (enunciado)'!D6*'T CR&AC'!C8 -> 50 | E8: =D8/D11 -> 0.4 | F8: =E8*'T Base (enunciado)'!D11 -> 1600 | G8: ='T Base (enunciado)'!E6*C8 -> 33.333333 | H8: =G8/G11 -> 0.25 | I8: =H8*'T Base (enunciado)'!E11 -> 1400 | J8: =F8+I8 -> 3000
B9: B | C9: ='T Base (enunciado)'!E26 -> 150 | D9: ='T Base (enunciado)'!D7*'T CR&AC'!C9 -> 75 | E9: =D9/D11 -> 0.6 | F9: =E9*'T Base (enunciado)'!D11 -> 2400 | G9: ='T Base (enunciado)'!E7*'T CR&AC'!C9 -> 100 | H9: =G9/G11 -> 0.75 | I9: =H9*'T Base (enunciado)'!E11 -> 4200 | J9: =F9+I9 -> 6600
B11: Total | D11: =D8+D9 -> 125 | E11: =E8+E9 -> 1 | F11: =F8+F9 -> 4000 | G11: =G8+G9 -> 133.33333 | H11: =H8+H9 -> 1 | I11: =I8+I9 -> 5600 | J11: =J8+J9 -> 9600

Sheet Resultados
B2: Produtos | C2: Ponto de Equilibrio
C4: (unidades por mês)
B6: A | C6: =D16 -> 40
B7: B | C7: =D17 -> 66
C10: Rce = | D10: ='T Participações Relativas'!E15*'T Participações Relativas'!E9+'T Participações Relativas'!F15*'T Participações Relativas'!F9 -> 0.6
C11: Roi = | D11: {='T Base (enunciado)'!D19:E19/D10} -> 8000 | E11: 0 | F11: $ por mês
C12: RoiA = | D12: ='T Participações Relativas'!E15*D11 -> 3200 | E12: $ por mês
C13: RoiB = | D13: ='T Participações Relativas'!F15*D11 -> 4800 | E13: $ por mês
C14: QoiA = | D14: =D12/'T Participações Relativas'!E4 -> 32 | E14: unidades por mês
C15: QoiB = | D15: =D13/'T Participações Relativas'!F4 -> 24 | E15: unidades por mês
C16: QodA = | D16: ='T CR&AC'!J8/('T Base (enunciado)'!D25-'T Base (enunciado)'!C6) -> 40 | F16: unidades por mês
C17: QodB = | D17: ='T CR&AC'!J9/('T Base (enunciado)'!D26-'T Base (enunciado)'!C7) -> 66 | F17: unidades por mês

Sheet Fórmulas
A1: ϖ | B1: Q | D1: V | F1: F
A2: Custo Total = | B2: Quantidade Produzida | C2: x | D2: Custo Variável Unitário | E2: + | F2: Custo Fixo
A3: =B3*D3+F3 -> 0
D4: P
A5: Receita Total = | B5: Quantidade Vendida | C5: x | D5: Preço Venda Unitário
A6: =B6*D6 -> 0
A8: Lucro = | B8: Receita Total | C8: - | D8: Custo Total
A9: =A3-A6 -> 0
A11: Se Quantidade Produzida = Quantidade Vendida
A12: Lucro = | B12: Quantidade | C12: x | D12: (Preço Venda - Custo Variável) | E12: - | F12: Custo Fixo
B13: =B3+B6/2 -> 0 | D13: =D6-D3 -> 0 | F13: =F3 -> 0
A15: Margem de Contribuição Unitária
A16: MCUx = | B16: Px | C16: - | D16: Vx
A18: Razão de Contribuição
A19: RCx = | B19: MCUx | C19: / | D19: Px
A21: Quantidade a ser produzida | B21: para cobrir custos indiretos | D21: para cobrir custos diretos
A22: Qox = | B22: Qoix | C22: + | D22: Qodx
A24: Receita total equilibrio | B24: Custo fixo indireto | D24: Razão de Contribuição da Empresa
A25: Roi = | B25: Fi | C25: / | D25: RCe
A28: Qodx = | B28: Fdx | C28: / | D28: (Px - Vx)
